optree/_C.cp39-win32.pyd
optree/_C.pyi
optree/__init__.py
optree/accessor.py
optree/dataclasses.py
optree/functools.py
optree/ops.py
optree/py.typed
optree/pytree.py
optree/registry.py
optree/treespec.py
optree/typing.py
optree/utils.py
optree/version.py
optree/integration/__init__.py
optree/integration/jax.py
optree/integration/numpy.py
optree/integration/torch.py
optree-0.15.0.dist-info/licenses/LICENSE
optree-0.15.0.dist-info/METADATA
optree-0.15.0.dist-info/WHEEL
optree-0.15.0.dist-info/top_level.txt
optree-0.15.0.dist-info/RECORD
