Metadata-Version: 2.1
Name: optree
Version: 0.15.0
Summary: Optimized PyTree Utilities.
Author: OpTree Contributors
Author-email: Xuehai Pan <XuehaiPan@pku.edu.cn>, Jie Ren <jieren9806@gmail.com>
License: Apache-2.0
Project-URL: Homepage, https://github.com/metaopt/optree
Project-URL: Repository, https://github.com/metaopt/optree
Project-URL: Documentation, https://optree.readthedocs.io
Project-URL: Bug Report, https://github.com/metaopt/optree/issues
Keywords: PyTree,Tree Manipulation,Tree Traversal,Functional Programming
Classifier: Development Status :: 4 - Beta
Classifier: License :: OSI Approved :: Apache Software License
Classifier: Programming Language :: C++
Classifier: Programming Language :: Python :: 3
Classifier: Programming Language :: Python :: 3.8
Classifier: Programming Language :: Python :: 3.9
Classifier: Programming Language :: Python :: 3.10
Classifier: Programming Language :: Python :: 3.11
Classifier: Programming Language :: Python :: 3.12
Classifier: Programming Language :: Python :: 3.13
Classifier: Programming Language :: Python :: Implementation :: CPython
Classifier: Programming Language :: Python :: Implementation :: PyPy
Classifier: Operating System :: Microsoft :: Windows
Classifier: Operating System :: POSIX :: Linux
Classifier: Operating System :: MacOS
Classifier: Intended Audience :: Developers
Classifier: Intended Audience :: Education
Classifier: Intended Audience :: Science/Research
Classifier: Topic :: Utilities
Requires-Python: >=3.8
License-File: LICENSE
Requires-Dist: typing-extensions >=4.5.0
Provides-Extra: benchmark
Requires-Dist: jax[cpu] <0.5.0a0,>=0.4.6 ; extra == 'benchmark'
Requires-Dist: torch <2.6.0a0,>=2.0 ; extra == 'benchmark'
Requires-Dist: torchvision ; extra == 'benchmark'
Requires-Dist: dm-tree <0.2.0a0,>=0.1 ; extra == 'benchmark'
Requires-Dist: pandas ; extra == 'benchmark'
Requires-Dist: tabulate ; extra == 'benchmark'
Requires-Dist: termcolor ; extra == 'benchmark'
Provides-Extra: docs
Requires-Dist: sphinx ; extra == 'docs'
Requires-Dist: sphinx-autoapi ; extra == 'docs'
Requires-Dist: sphinx-autobuild ; extra == 'docs'
Requires-Dist: sphinx-copybutton ; extra == 'docs'
Requires-Dist: sphinx-rtd-theme ; extra == 'docs'
Requires-Dist: sphinxcontrib-bibtex ; extra == 'docs'
Requires-Dist: sphinx-autodoc-typehints ; extra == 'docs'
Requires-Dist: docutils ; extra == 'docs'
Requires-Dist: jax[cpu] ; extra == 'docs'
Requires-Dist: numpy ; extra == 'docs'
Requires-Dist: torch ; extra == 'docs'
Provides-Extra: jax
Requires-Dist: jax ; extra == 'jax'
Provides-Extra: lint
Requires-Dist: ruff ; extra == 'lint'
Requires-Dist: pylint[spelling] ; extra == 'lint'
Requires-Dist: mypy ; extra == 'lint'
Requires-Dist: doc8 ; extra == 'lint'
Requires-Dist: pyenchant ; extra == 'lint'
Requires-Dist: xdoctest ; extra == 'lint'
Requires-Dist: cpplint ; extra == 'lint'
Requires-Dist: pre-commit ; extra == 'lint'
Provides-Extra: numpy
Requires-Dist: numpy ; extra == 'numpy'
Provides-Extra: test
Requires-Dist: pytest ; extra == 'test'
Requires-Dist: pytest-cov ; extra == 'test'
Requires-Dist: pytest-xdist ; extra == 'test'
Requires-Dist: covdefaults ; extra == 'test'
Provides-Extra: torch
Requires-Dist: torch ; extra == 'torch'
